odoo9_addon_l10n_es-9.0.1.1.0-py2.7-nspkg.pth
odoo9_addon_l10n_es-9.0.1.1.0.dist-info/DESCRIPTION.rst
odoo9_addon_l10n_es-9.0.1.1.0.dist-info/METADATA
odoo9_addon_l10n_es-9.0.1.1.0.dist-info/RECORD
odoo9_addon_l10n_es-9.0.1.1.0.dist-info/WHEEL
odoo9_addon_l10n_es-9.0.1.1.0.dist-info/metadata.json
odoo9_addon_l10n_es-9.0.1.1.0.dist-info/namespace_packages.txt
odoo9_addon_l10n_es-9.0.1.1.0.dist-info/top_level.txt
odoo_addons/l10n_es/README.rst
odoo_addons/l10n_es/__init__.py
odoo_addons/l10n_es/__openerp__.py
odoo_addons/l10n_es/data/account_account_assoc.xml
odoo_addons/l10n_es/data/account_account_common.xml
odoo_addons/l10n_es/data/account_account_full.xml
odoo_addons/l10n_es/data/account_account_pymes.xml
odoo_addons/l10n_es/data/account_chart_template.xml
odoo_addons/l10n_es/data/account_chart_template_post.xml
odoo_addons/l10n_es/data/account_type.xml
odoo_addons/l10n_es/data/fiscal_positions_common.xml
odoo_addons/l10n_es/data/tax_codes_common.xml
odoo_addons/l10n_es/data/taxes_common.xml
odoo_addons/l10n_es/i18n/ar.po
odoo_addons/l10n_es/i18n/ca.po
odoo_addons/l10n_es/i18n/da.po
odoo_addons/l10n_es/i18n/de.po
odoo_addons/l10n_es/i18n/es.po
odoo_addons/l10n_es/i18n/es_CR.po
odoo_addons/l10n_es/i18n/es_MX.po
odoo_addons/l10n_es/i18n/es_PY.po
odoo_addons/l10n_es/i18n/es_VE.po
odoo_addons/l10n_es/i18n/fr.po
odoo_addons/l10n_es/i18n/gl.po
odoo_addons/l10n_es/i18n/hu.po
odoo_addons/l10n_es/i18n/it.po
odoo_addons/l10n_es/i18n/nl.po
odoo_addons/l10n_es/i18n/oc.po
odoo_addons/l10n_es/i18n/pt.po
odoo_addons/l10n_es/i18n/pt_BR.po
odoo_addons/l10n_es/i18n/sl.po
odoo_addons/l10n_es/i18n/sr@latin.po
odoo_addons/l10n_es/i18n/tr.po
odoo_addons/l10n_es/images/config_chart_l10n_es.png
odoo_addons/l10n_es/images/l10n_es_chart.png
odoo_addons/l10n_es/static/description/icon.png
odoo_addons/l10n_es/tests/__init__.py
odoo_addons/l10n_es/tests/test_l10n_es.py
